{
  "id": "wh-12345",
  "name": "Main Building Water Heater",
  "model": "IoTSphere Pro 5000",
  "location": "Basement Utility Room",
  "status": {
    "operational": true,
    "alert_level": "warning",
    "condition": "abnormal_temperature"
  },
  "metrics": {
    "current_temperature": 155,
    "target_temperature": 120,
    "units": "fahrenheit",
    "pressure": 65,
    "flow_rate": 12.5,
    "energy_usage": 4.8
  },
  "telemetry": {
    "temperature": 155,
    "target_temperature": 120,
    "heating_status": "warning",
    "power_status": "on",
    "water_flow": 12.5,
    "timestamp": "2025-04-10T14:15:23Z"
  },
  "maintenance": {
    "last_service": "2025-01-15",
    "next_service_due": "2025-07-15",
    "service_history": []
  },
  "alerts": [
    {
      "type": "temperature",
      "severity": "warning",
      "message": "Temperature above normal range",
      "timestamp": "2025-04-10T10:23:45"
    }
  ]
}
